whats_api
