Metadata-Version: 2.1
Name: whats-api
Version: 1.0.1
Summary: Open source module for sending messages to WhatsApp based on Selenium
Home-page: https://github.com/neluckoff/whats_api/archive/main.zip
Author: neluckoff
Author-email: neluckoff@gmail.com
License: MIT License, see LICENSE file
Download-URL: https://github.com/neluckoff/whats_api/archive/master.zip
Platform: UNKNOWN
Classifier: License :: OSI Approved :: MIT License
Classifier: Operating System :: Unix
Classifier: Operating System :: MacOS :: MacOS X
Classifier: Operating System :: Microsoft :: Windows
Classifier: Intended Audience :: End Users/Desktop
Classifier: Intended Audience :: Developers
Classifier: Programming Language :: Python
Classifier: Programming Language :: Python :: 3
Classifier: Programming Language :: Python :: 3.6
Classifier: Programming Language :: Python :: 3.7
Classifier: Programming Language :: Python :: 3.8
License-File: LICENSE
